{
    "_links": {
        "comments": {
            "href": "https://api.github.com/repos/venomous0x/WhatsAPI/issues/631/comments"
        },
        "commits": {
            "href": "https://api.github.com/repos/venomous0x/WhatsAPI/pulls/631/commits"
        },
        "html": {
            "href": "https://github.com/venomous0x/WhatsAPI/pull/631"
        },
        "issue": {
            "href": "https://api.github.com/repos/venomous0x/WhatsAPI/issues/631"
        },
        "review_comment": {
            "href": "https://api.github.com/repos/venomous0x/WhatsAPI/pulls/comments{/number}"
        },
        "review_comments": {
            "href": "https://api.github.com/repos/venomous0x/WhatsAPI/pulls/631/comments"
        },
        "self": {
            "href": "https://api.github.com/repos/venomous0x/WhatsAPI/pulls/631"
        },
        "statuses": {
            "href": "https://api.github.com/repos/venomous0x/WhatsAPI/statuses/359f95f6f510435d997ce1befc710cf91023ca09"
        }
    },
    "assignee": null,
    "base": {
        "label": "venomous0x:master",
        "ref": "master",
        "repo": {
            "archive_url": "https://api.github.com/repos/venomous0x/WhatsAPI/{archive_format}{/ref}",
            "assignees_url": "https://api.github.com/repos/venomous0x/WhatsAPI/assignees{/user}",
            "blobs_url": "https://api.github.com/repos/venomous0x/WhatsAPI/git/blobs{/sha}",
            "branches_url": "https://api.github.com/repos/venomous0x/WhatsAPI/branches{/branch}",
            "clone_url": "https://github.com/venomous0x/WhatsAPI.git",
            "collaborators_url": "https://api.github.com/repos/venomous0x/WhatsAPI/collaborators{/collaborator}",
            "comments_url": "https://api.github.com/repos/venomous0x/WhatsAPI/comments{/number}",
            "commits_url": "https://api.github.com/repos/venomous0x/WhatsAPI/commits{/sha}",
            "compare_url": "https://api.github.com/repos/venomous0x/WhatsAPI/compare/{base}...{head}",
            "contents_url": "https://api.github.com/repos/venomous0x/WhatsAPI/contents/{+path}",
            "contributors_url": "https://api.github.com/repos/venomous0x/WhatsAPI/contributors",
            "created_at": "2012-05-28T16:29:46Z",
            "default_branch": "master",
            "description": "Interface to WhatsApp Messenger",
            "downloads_url": "https://api.github.com/repos/venomous0x/WhatsAPI/downloads",
            "events_url": "https://api.github.com/repos/venomous0x/WhatsAPI/events",
            "fork": false,
            "forks": 1935,
            "forks_count": 1935,
            "forks_url": "https://api.github.com/repos/venomous0x/WhatsAPI/forks",
            "full_name": "venomous0x/WhatsAPI",
            "git_commits_url": "https://api.github.com/repos/venomous0x/WhatsAPI/git/commits{/sha}",
            "git_refs_url": "https://api.github.com/repos/venomous0x/WhatsAPI/git/refs{/sha}",
            "git_tags_url": "https://api.github.com/repos/venomous0x/WhatsAPI/git/tags{/sha}",
            "git_url": "git://github.com/venomous0x/WhatsAPI.git",
            "has_downloads": true,
            "has_issues": true,
            "has_pages": false,
            "has_wiki": true,
            "homepage": "",
            "hooks_url": "https://api.github.com/repos/venomous0x/WhatsAPI/hooks",
            "html_url": "https://github.com/venomous0x/WhatsAPI",
            "id": 4472401,
            "issue_comment_url": "https://api.github.com/repos/venomous0x/WhatsAPI/issues/comments{/number}",
            "issue_events_url": "https://api.github.com/repos/venomous0x/WhatsAPI/issues/events{/number}",
            "issues_url": "https://api.github.com/repos/venomous0x/WhatsAPI/issues{/number}",
            "keys_url": "https://api.github.com/repos/venomous0x/WhatsAPI/keys{/key_id}",
            "labels_url": "https://api.github.com/repos/venomous0x/WhatsAPI/labels{/name}",
            "language": null,
            "languages_url": "https://api.github.com/repos/venomous0x/WhatsAPI/languages",
            "merges_url": "https://api.github.com/repos/venomous0x/WhatsAPI/merges",
            "milestones_url": "https://api.github.com/repos/venomous0x/WhatsAPI/milestones{/number}",
            "mirror_url": null,
            "name": "WhatsAPI",
            "notifications_url": "https://api.github.com/repos/venomous0x/WhatsAPI/notifications{?since,all,participating}",
            "open_issues": 528,
            "open_issues_count": 528,
            "owner": {
                "avatar_url": "https://avatars.githubusercontent.com/u/1786115?v=3",
                "events_url": "https://api.github.com/users/venomous0x/events{/privacy}",
                "followers_url": "https://api.github.com/users/venomous0x/followers",
                "following_url": "https://api.github.com/users/venomous0x/following{/other_user}",
                "gists_url": "https://api.github.com/users/venomous0x/gists{/gist_id}",
                "gravatar_id": "",
                "html_url": "https://github.com/venomous0x",
                "id": 1786115,
                "login": "venomous0x",
                "organizations_url": "https://api.github.com/users/venomous0x/orgs",
                "received_events_url": "https://api.github.com/users/venomous0x/received_events",
                "repos_url": "https://api.github.com/users/venomous0x/repos",
                "site_admin": false,
                "starred_url": "https://api.github.com/users/venomous0x/starred{/owner}{/repo}",
                "subscriptions_url": "https://api.github.com/users/venomous0x/subscriptions",
                "type": "Organization",
                "url": "https://api.github.com/users/venomous0x"
            },
            "private": false,
            "pulls_url": "https://api.github.com/repos/venomous0x/WhatsAPI/pulls{/number}",
            "pushed_at": "2015-05-03T17:53:48Z",
            "releases_url": "https://api.github.com/repos/venomous0x/WhatsAPI/releases{/id}",
            "size": 3191,
            "ssh_url": "git@github.com:venomous0x/WhatsAPI.git",
            "stargazers_count": 2481,
            "stargazers_url": "https://api.github.com/repos/venomous0x/WhatsAPI/stargazers",
            "statuses_url": "https://api.github.com/repos/venomous0x/WhatsAPI/statuses/{sha}",
            "subscribers_url": "https://api.github.com/repos/venomous0x/WhatsAPI/subscribers",
            "subscription_url": "https://api.github.com/repos/venomous0x/WhatsAPI/subscription",
            "svn_url": "https://github.com/venomous0x/WhatsAPI",
            "tags_url": "https://api.github.com/repos/venomous0x/WhatsAPI/tags",
            "teams_url": "https://api.github.com/repos/venomous0x/WhatsAPI/teams",
            "trees_url": "https://api.github.com/repos/venomous0x/WhatsAPI/git/trees{/sha}",
            "updated_at": "2015-05-20T22:40:28Z",
            "url": "https://api.github.com/repos/venomous0x/WhatsAPI",
            "watchers": 2481,
            "watchers_count": 2481
        },
        "sha": "e980346b777c047349a2992a1deb8f89c5eb9918",
        "user": {
            "avatar_url": "https://avatars.githubusercontent.com/u/1786115?v=3",
            "events_url": "https://api.github.com/users/venomous0x/events{/privacy}",
            "followers_url": "https://api.github.com/users/venomous0x/followers",
            "following_url": "https://api.github.com/users/venomous0x/following{/other_user}",
            "gists_url": "https://api.github.com/users/venomous0x/gists{/gist_id}",
            "gravatar_id": "",
            "html_url": "https://github.com/venomous0x",
            "id": 1786115,
            "login": "venomous0x",
            "organizations_url": "https://api.github.com/users/venomous0x/orgs",
            "received_events_url": "https://api.github.com/users/venomous0x/received_events",
            "repos_url": "https://api.github.com/users/venomous0x/repos",
            "site_admin": false,
            "starred_url": "https://api.github.com/users/venomous0x/starred{/owner}{/repo}",
            "subscriptions_url": "https://api.github.com/users/venomous0x/subscriptions",
            "type": "Organization",
            "url": "https://api.github.com/users/venomous0x"
        }
    },
    "body": "This change is very helpful when using the events and want to print this object or convert it to JSON format.\r\n\r\nFor example:\r\n\r\n```php\r\n    /**\r\n     * Event fired when was get an error\r\n     *\r\n     * @param string $phone\r\n     * @param \\WhatsApi\\Nodes\\ProtocolNode $error\r\n     */\r\n    public function onGetError(\r\n      $phone,\r\n      $error\r\n    )\r\n    {\r\n      $result = array(\r\n        'sender' => $phone,\r\n        'error'  => (string)$error  //Casting to force object conversion to string\r\n      );\r\n\r\n      echo json_encode( $result );\r\n    }",
    "closed_at": "2014-03-18T02:55:35Z",
    "comment_data": [],
    "comments_url": "https://api.github.com/repos/venomous0x/WhatsAPI/issues/631/comments",
    "commit_data": [
        {
            "author": {
                "avatar_url": "https://avatars.githubusercontent.com/u/594574?v=3",
                "events_url": "https://api.github.com/users/rafa-aguilar/events{/privacy}",
                "followers_url": "https://api.github.com/users/rafa-aguilar/followers",
                "following_url": "https://api.github.com/users/rafa-aguilar/following{/other_user}",
                "gists_url": "https://api.github.com/users/rafa-aguilar/gists{/gist_id}",
                "gravatar_id": "",
                "html_url": "https://github.com/rafa-aguilar",
                "id": 594574,
                "login": "rafa-aguilar",
                "organizations_url": "https://api.github.com/users/rafa-aguilar/orgs",
                "received_events_url": "https://api.github.com/users/rafa-aguilar/received_events",
                "repos_url": "https://api.github.com/users/rafa-aguilar/repos",
                "site_admin": false,
                "starred_url": "https://api.github.com/users/rafa-aguilar/starred{/owner}{/repo}",
                "subscriptions_url": "https://api.github.com/users/rafa-aguilar/subscriptions",
                "type": "User",
                "url": "https://api.github.com/users/rafa-aguilar"
            },
            "comments_url": "https://api.github.com/repos/venomous0x/WhatsAPI/commits/359f95f6f510435d997ce1befc710cf91023ca09/comments",
            "commit": {
                "author": {
                    "date": "2014-03-18T02:52:08Z",
                    "email": "rafaaguilar88@gmail.com",
                    "name": "Rafa Aguilar"
                },
                "comment_count": 0,
                "committer": {
                    "date": "2014-03-18T02:52:08Z",
                    "email": "rafaaguilar88@gmail.com",
                    "name": "Rafa Aguilar"
                },
                "message": "Add toString method to ProtocolNode class\n\nThis change is very helpful when using the events and want to print this object or convert it to JSON format.\r\n\r\nFor example:\r\n\r\n```php\r\n    /**\r\n     * Event fired when was get an error\r\n     *\r\n     * @param string $phone\r\n     * @param \\WhatsApi\\Nodes\\ProtocolNode $error\r\n     */\r\n    public function onGetError(\r\n      $phone,\r\n      $error\r\n    )\r\n    {\r\n      $result = array(\r\n        'sender' => $phone,\r\n        'error'  => (string)$error  //Casting to force object conversion to string\r\n      );\r\n\r\n      echo json_encode( $result );\r\n    }",
                "tree": {
                    "sha": "9a628c0d78ba5b364cb763a909b9146ec0a0a13b",
                    "url": "https://api.github.com/repos/venomous0x/WhatsAPI/git/trees/9a628c0d78ba5b364cb763a909b9146ec0a0a13b"
                },
                "url": "https://api.github.com/repos/venomous0x/WhatsAPI/git/commits/359f95f6f510435d997ce1befc710cf91023ca09"
            },
            "committer": {
                "avatar_url": "https://avatars.githubusercontent.com/u/594574?v=3",
                "events_url": "https://api.github.com/users/rafa-aguilar/events{/privacy}",
                "followers_url": "https://api.github.com/users/rafa-aguilar/followers",
                "following_url": "https://api.github.com/users/rafa-aguilar/following{/other_user}",
                "gists_url": "https://api.github.com/users/rafa-aguilar/gists{/gist_id}",
                "gravatar_id": "",
                "html_url": "https://github.com/rafa-aguilar",
                "id": 594574,
                "login": "rafa-aguilar",
                "organizations_url": "https://api.github.com/users/rafa-aguilar/orgs",
                "received_events_url": "https://api.github.com/users/rafa-aguilar/received_events",
                "repos_url": "https://api.github.com/users/rafa-aguilar/repos",
                "site_admin": false,
                "starred_url": "https://api.github.com/users/rafa-aguilar/starred{/owner}{/repo}",
                "subscriptions_url": "https://api.github.com/users/rafa-aguilar/subscriptions",
                "type": "User",
                "url": "https://api.github.com/users/rafa-aguilar"
            },
            "html_url": "https://github.com/venomous0x/WhatsAPI/commit/359f95f6f510435d997ce1befc710cf91023ca09",
            "parents": [
                {
                    "html_url": "https://github.com/venomous0x/WhatsAPI/commit/e980346b777c047349a2992a1deb8f89c5eb9918",
                    "sha": "e980346b777c047349a2992a1deb8f89c5eb9918",
                    "url": "https://api.github.com/repos/venomous0x/WhatsAPI/commits/e980346b777c047349a2992a1deb8f89c5eb9918"
                }
            ],
            "sha": "359f95f6f510435d997ce1befc710cf91023ca09",
            "url": "https://api.github.com/repos/venomous0x/WhatsAPI/commits/359f95f6f510435d997ce1befc710cf91023ca09"
        }
    ],
    "commits_url": "https://api.github.com/repos/venomous0x/WhatsAPI/pulls/631/commits",
    "created_at": "2014-03-18T02:53:07Z",
    "diff_url": "https://github.com/venomous0x/WhatsAPI/pull/631.diff",
    "head": {
        "label": "rafa-aguilar:patch-2",
        "ref": "patch-2",
        "repo": {
            "archive_url": "https://api.github.com/repos/rafa-aguilar/WhatsAPI/{archive_format}{/ref}",
            "assignees_url": "https://api.github.com/repos/rafa-aguilar/WhatsAPI/assignees{/user}",
            "blobs_url": "https://api.github.com/repos/rafa-aguilar/WhatsAPI/git/blobs{/sha}",
            "branches_url": "https://api.github.com/repos/rafa-aguilar/WhatsAPI/branches{/branch}",
            "clone_url": "https://github.com/rafa-aguilar/WhatsAPI.git",
            "collaborators_url": "https://api.github.com/repos/rafa-aguilar/WhatsAPI/collaborators{/collaborator}",
            "comments_url": "https://api.github.com/repos/rafa-aguilar/WhatsAPI/comments{/number}",
            "commits_url": "https://api.github.com/repos/rafa-aguilar/WhatsAPI/commits{/sha}",
            "compare_url": "https://api.github.com/repos/rafa-aguilar/WhatsAPI/compare/{base}...{head}",
            "contents_url": "https://api.github.com/repos/rafa-aguilar/WhatsAPI/contents/{+path}",
            "contributors_url": "https://api.github.com/repos/rafa-aguilar/WhatsAPI/contributors",
            "created_at": "2014-03-03T14:06:34Z",
            "default_branch": "master",
            "description": "Packagist PHP Interface to WhatsApp Messenger",
            "downloads_url": "https://api.github.com/repos/rafa-aguilar/WhatsAPI/downloads",
            "events_url": "https://api.github.com/repos/rafa-aguilar/WhatsAPI/events",
            "fork": true,
            "forks": 2,
            "forks_count": 2,
            "forks_url": "https://api.github.com/repos/rafa-aguilar/WhatsAPI/forks",
            "full_name": "rafa-aguilar/WhatsAPI",
            "git_commits_url": "https://api.github.com/repos/rafa-aguilar/WhatsAPI/git/commits{/sha}",
            "git_refs_url": "https://api.github.com/repos/rafa-aguilar/WhatsAPI/git/refs{/sha}",
            "git_tags_url": "https://api.github.com/repos/rafa-aguilar/WhatsAPI/git/tags{/sha}",
            "git_url": "git://github.com/rafa-aguilar/WhatsAPI.git",
            "has_downloads": true,
            "has_issues": true,
            "has_pages": false,
            "has_wiki": true,
            "homepage": "https://packagist.org/packages/whatsapi/whatsapi",
            "hooks_url": "https://api.github.com/repos/rafa-aguilar/WhatsAPI/hooks",
            "html_url": "https://github.com/rafa-aguilar/WhatsAPI",
            "id": 17367817,
            "issue_comment_url": "https://api.github.com/repos/rafa-aguilar/WhatsAPI/issues/comments{/number}",
            "issue_events_url": "https://api.github.com/repos/rafa-aguilar/WhatsAPI/issues/events{/number}",
            "issues_url": "https://api.github.com/repos/rafa-aguilar/WhatsAPI/issues{/number}",
            "keys_url": "https://api.github.com/repos/rafa-aguilar/WhatsAPI/keys{/key_id}",
            "labels_url": "https://api.github.com/repos/rafa-aguilar/WhatsAPI/labels{/name}",
            "language": "PHP",
            "languages_url": "https://api.github.com/repos/rafa-aguilar/WhatsAPI/languages",
            "merges_url": "https://api.github.com/repos/rafa-aguilar/WhatsAPI/merges",
            "milestones_url": "https://api.github.com/repos/rafa-aguilar/WhatsAPI/milestones{/number}",
            "mirror_url": null,
            "name": "WhatsAPI",
            "notifications_url": "https://api.github.com/repos/rafa-aguilar/WhatsAPI/notifications{?since,all,participating}",
            "open_issues": 0,
            "open_issues_count": 0,
            "owner": {
                "avatar_url": "https://avatars.githubusercontent.com/u/594574?v=3",
                "events_url": "https://api.github.com/users/rafa-aguilar/events{/privacy}",
                "followers_url": "https://api.github.com/users/rafa-aguilar/followers",
                "following_url": "https://api.github.com/users/rafa-aguilar/following{/other_user}",
                "gists_url": "https://api.github.com/users/rafa-aguilar/gists{/gist_id}",
                "gravatar_id": "",
                "html_url": "https://github.com/rafa-aguilar",
                "id": 594574,
                "login": "rafa-aguilar",
                "organizations_url": "https://api.github.com/users/rafa-aguilar/orgs",
                "received_events_url": "https://api.github.com/users/rafa-aguilar/received_events",
                "repos_url": "https://api.github.com/users/rafa-aguilar/repos",
                "site_admin": false,
                "starred_url": "https://api.github.com/users/rafa-aguilar/starred{/owner}{/repo}",
                "subscriptions_url": "https://api.github.com/users/rafa-aguilar/subscriptions",
                "type": "User",
                "url": "https://api.github.com/users/rafa-aguilar"
            },
            "private": false,
            "pulls_url": "https://api.github.com/repos/rafa-aguilar/WhatsAPI/pulls{/number}",
            "pushed_at": "2014-03-30T15:40:48Z",
            "releases_url": "https://api.github.com/repos/rafa-aguilar/WhatsAPI/releases{/id}",
            "size": 2519,
            "ssh_url": "git@github.com:rafa-aguilar/WhatsAPI.git",
            "stargazers_count": 2,
            "stargazers_url": "https://api.github.com/repos/rafa-aguilar/WhatsAPI/stargazers",
            "statuses_url": "https://api.github.com/repos/rafa-aguilar/WhatsAPI/statuses/{sha}",
            "subscribers_url": "https://api.github.com/repos/rafa-aguilar/WhatsAPI/subscribers",
            "subscription_url": "https://api.github.com/repos/rafa-aguilar/WhatsAPI/subscription",
            "svn_url": "https://github.com/rafa-aguilar/WhatsAPI",
            "tags_url": "https://api.github.com/repos/rafa-aguilar/WhatsAPI/tags",
            "teams_url": "https://api.github.com/repos/rafa-aguilar/WhatsAPI/teams",
            "trees_url": "https://api.github.com/repos/rafa-aguilar/WhatsAPI/git/trees{/sha}",
            "updated_at": "2015-03-18T20:39:52Z",
            "url": "https://api.github.com/repos/rafa-aguilar/WhatsAPI",
            "watchers": 2,
            "watchers_count": 2
        },
        "sha": "359f95f6f510435d997ce1befc710cf91023ca09",
        "user": {
            "avatar_url": "https://avatars.githubusercontent.com/u/594574?v=3",
            "events_url": "https://api.github.com/users/rafa-aguilar/events{/privacy}",
            "followers_url": "https://api.github.com/users/rafa-aguilar/followers",
            "following_url": "https://api.github.com/users/rafa-aguilar/following{/other_user}",
            "gists_url": "https://api.github.com/users/rafa-aguilar/gists{/gist_id}",
            "gravatar_id": "",
            "html_url": "https://github.com/rafa-aguilar",
            "id": 594574,
            "login": "rafa-aguilar",
            "organizations_url": "https://api.github.com/users/rafa-aguilar/orgs",
            "received_events_url": "https://api.github.com/users/rafa-aguilar/received_events",
            "repos_url": "https://api.github.com/users/rafa-aguilar/repos",
            "site_admin": false,
            "starred_url": "https://api.github.com/users/rafa-aguilar/starred{/owner}{/repo}",
            "subscriptions_url": "https://api.github.com/users/rafa-aguilar/subscriptions",
            "type": "User",
            "url": "https://api.github.com/users/rafa-aguilar"
        }
    },
    "html_url": "https://github.com/venomous0x/WhatsAPI/pull/631",
    "id": 13667189,
    "issue_url": "https://api.github.com/repos/venomous0x/WhatsAPI/issues/631",
    "locked": false,
    "merge_commit_sha": "2b31a5839da0a2df507fdd1caae63a956481fe2b",
    "merged_at": null,
    "milestone": null,
    "number": 631,
    "patch_url": "https://github.com/venomous0x/WhatsAPI/pull/631.patch",
    "review_comment_url": "https://api.github.com/repos/venomous0x/WhatsAPI/pulls/comments{/number}",
    "review_comments_url": "https://api.github.com/repos/venomous0x/WhatsAPI/pulls/631/comments",
    "state": "closed",
    "statuses_url": "https://api.github.com/repos/venomous0x/WhatsAPI/statuses/359f95f6f510435d997ce1befc710cf91023ca09",
    "title": "Add toString method to ProtocolNode class",
    "updated_at": "2014-07-06T23:38:37Z",
    "url": "https://api.github.com/repos/venomous0x/WhatsAPI/pulls/631",
    "user": {
        "avatar_url": "https://avatars.githubusercontent.com/u/594574?v=3",
        "events_url": "https://api.github.com/users/rafa-aguilar/events{/privacy}",
        "followers_url": "https://api.github.com/users/rafa-aguilar/followers",
        "following_url": "https://api.github.com/users/rafa-aguilar/following{/other_user}",
        "gists_url": "https://api.github.com/users/rafa-aguilar/gists{/gist_id}",
        "gravatar_id": "",
        "html_url": "https://github.com/rafa-aguilar",
        "id": 594574,
        "login": "rafa-aguilar",
        "organizations_url": "https://api.github.com/users/rafa-aguilar/orgs",
        "received_events_url": "https://api.github.com/users/rafa-aguilar/received_events",
        "repos_url": "https://api.github.com/users/rafa-aguilar/repos",
        "site_admin": false,
        "starred_url": "https://api.github.com/users/rafa-aguilar/starred{/owner}{/repo}",
        "subscriptions_url": "https://api.github.com/users/rafa-aguilar/subscriptions",
        "type": "User",
        "url": "https://api.github.com/users/rafa-aguilar"
    }
}