{
    "assignee": null,
    "body": "Hi ,\r\nI m trying ContactSync i getting this error \"The remote server returned an error: (404) Not Found.\" when i over _executeSync method . Even i have changed WAUTH-1 to WAUTH-2..\r\n\r\nI need Help ...",
    "closed_at": "2014-02-08T12:54:19Z",
    "comment_data": [
        {
            "body": "Please do not post the same thing everywhere.\r\nI see you have already posted it here - https://github.com/venomous0x/WhatsAPI/issues/571, you should probably read the previous comments on the issue before trying to spam!",
            "created_at": "2014-02-08T11:46:20Z",
            "html_url": "https://github.com/venomous0x/WhatsAPI/issues/616#issuecomment-34541864",
            "id": 34541864,
            "issue_url": "https://api.github.com/repos/venomous0x/WhatsAPI/issues/616",
            "updated_at": "2014-02-08T11:46:20Z",
            "url": "https://api.github.com/repos/venomous0x/WhatsAPI/issues/comments/34541864",
            "user": {
                "avatar_url": "https://avatars.githubusercontent.com/u/692559?v=3",
                "events_url": "https://api.github.com/users/mayankgupta/events{/privacy}",
                "followers_url": "https://api.github.com/users/mayankgupta/followers",
                "following_url": "https://api.github.com/users/mayankgupta/following{/other_user}",
                "gists_url": "https://api.github.com/users/mayankgupta/gists{/gist_id}",
                "gravatar_id": "",
                "html_url": "https://github.com/mayankgupta",
                "id": 692559,
                "login": "mayankgupta",
                "organizations_url": "https://api.github.com/users/mayankgupta/orgs",
                "received_events_url": "https://api.github.com/users/mayankgupta/received_events",
                "repos_url": "https://api.github.com/users/mayankgupta/repos",
                "site_admin": false,
                "starred_url": "https://api.github.com/users/mayankgupta/starred{/owner}{/repo}",
                "subscriptions_url": "https://api.github.com/users/mayankgupta/subscriptions",
                "type": "User",
                "url": "https://api.github.com/users/mayankgupta"
            }
        },
        {
            "body": "Duplicate #571\r\n\r\nand this is your problem and not ours, so behave yourself if you want some help.",
            "created_at": "2014-02-08T12:54:19Z",
            "html_url": "https://github.com/venomous0x/WhatsAPI/issues/616#issuecomment-34543302",
            "id": 34543302,
            "issue_url": "https://api.github.com/repos/venomous0x/WhatsAPI/issues/616",
            "updated_at": "2014-02-08T12:54:19Z",
            "url": "https://api.github.com/repos/venomous0x/WhatsAPI/issues/comments/34543302",
            "user": {
                "avatar_url": "https://avatars.githubusercontent.com/u/1610953?v=3",
                "events_url": "https://api.github.com/users/shirioko/events{/privacy}",
                "followers_url": "https://api.github.com/users/shirioko/followers",
                "following_url": "https://api.github.com/users/shirioko/following{/other_user}",
                "gists_url": "https://api.github.com/users/shirioko/gists{/gist_id}",
                "gravatar_id": "",
                "html_url": "https://github.com/shirioko",
                "id": 1610953,
                "login": "shirioko",
                "organizations_url": "https://api.github.com/users/shirioko/orgs",
                "received_events_url": "https://api.github.com/users/shirioko/received_events",
                "repos_url": "https://api.github.com/users/shirioko/repos",
                "site_admin": false,
                "starred_url": "https://api.github.com/users/shirioko/starred{/owner}{/repo}",
                "subscriptions_url": "https://api.github.com/users/shirioko/subscriptions",
                "type": "User",
                "url": "https://api.github.com/users/shirioko"
            }
        },
        {
            "body": "ok fine ..i got another solution ....thanks for behave..bye :)",
            "created_at": "2014-02-08T13:45:10Z",
            "html_url": "https://github.com/venomous0x/WhatsAPI/issues/616#issuecomment-34544232",
            "id": 34544232,
            "issue_url": "https://api.github.com/repos/venomous0x/WhatsAPI/issues/616",
            "updated_at": "2014-02-08T13:45:10Z",
            "url": "https://api.github.com/repos/venomous0x/WhatsAPI/issues/comments/34544232",
            "user": {
                "avatar_url": "https://avatars.githubusercontent.com/u/6623848?v=3",
                "events_url": "https://api.github.com/users/kmpslm/events{/privacy}",
                "followers_url": "https://api.github.com/users/kmpslm/followers",
                "following_url": "https://api.github.com/users/kmpslm/following{/other_user}",
                "gists_url": "https://api.github.com/users/kmpslm/gists{/gist_id}",
                "gravatar_id": "",
                "html_url": "https://github.com/kmpslm",
                "id": 6623848,
                "login": "kmpslm",
                "organizations_url": "https://api.github.com/users/kmpslm/orgs",
                "received_events_url": "https://api.github.com/users/kmpslm/received_events",
                "repos_url": "https://api.github.com/users/kmpslm/repos",
                "site_admin": false,
                "starred_url": "https://api.github.com/users/kmpslm/starred{/owner}{/repo}",
                "subscriptions_url": "https://api.github.com/users/kmpslm/subscriptions",
                "type": "User",
                "url": "https://api.github.com/users/kmpslm"
            }
        },
        {
            "body": "@kmpslm: If you don't mind, can you post your solution?",
            "created_at": "2014-02-08T13:48:35Z",
            "html_url": "https://github.com/venomous0x/WhatsAPI/issues/616#issuecomment-34544286",
            "id": 34544286,
            "issue_url": "https://api.github.com/repos/venomous0x/WhatsAPI/issues/616",
            "updated_at": "2014-02-08T13:48:35Z",
            "url": "https://api.github.com/repos/venomous0x/WhatsAPI/issues/comments/34544286",
            "user": {
                "avatar_url": "https://avatars.githubusercontent.com/u/6607651?v=3",
                "events_url": "https://api.github.com/users/marknick/events{/privacy}",
                "followers_url": "https://api.github.com/users/marknick/followers",
                "following_url": "https://api.github.com/users/marknick/following{/other_user}",
                "gists_url": "https://api.github.com/users/marknick/gists{/gist_id}",
                "gravatar_id": "",
                "html_url": "https://github.com/marknick",
                "id": 6607651,
                "login": "marknick",
                "organizations_url": "https://api.github.com/users/marknick/orgs",
                "received_events_url": "https://api.github.com/users/marknick/received_events",
                "repos_url": "https://api.github.com/users/marknick/repos",
                "site_admin": false,
                "starred_url": "https://api.github.com/users/marknick/starred{/owner}{/repo}",
                "subscriptions_url": "https://api.github.com/users/marknick/subscriptions",
                "type": "User",
                "url": "https://api.github.com/users/marknick"
            }
        },
        {
            "body": "We appreciate your approach. Please can you post your solution?\r\n",
            "created_at": "2014-02-08T15:57:44Z",
            "html_url": "https://github.com/venomous0x/WhatsAPI/issues/616#issuecomment-34547413",
            "id": 34547413,
            "issue_url": "https://api.github.com/repos/venomous0x/WhatsAPI/issues/616",
            "updated_at": "2014-02-08T15:57:44Z",
            "url": "https://api.github.com/repos/venomous0x/WhatsAPI/issues/comments/34547413",
            "user": {
                "avatar_url": "https://avatars.githubusercontent.com/u/6393142?v=3",
                "events_url": "https://api.github.com/users/faisalcse/events{/privacy}",
                "followers_url": "https://api.github.com/users/faisalcse/followers",
                "following_url": "https://api.github.com/users/faisalcse/following{/other_user}",
                "gists_url": "https://api.github.com/users/faisalcse/gists{/gist_id}",
                "gravatar_id": "",
                "html_url": "https://github.com/faisalcse",
                "id": 6393142,
                "login": "faisalcse",
                "organizations_url": "https://api.github.com/users/faisalcse/orgs",
                "received_events_url": "https://api.github.com/users/faisalcse/received_events",
                "repos_url": "https://api.github.com/users/faisalcse/repos",
                "site_admin": false,
                "starred_url": "https://api.github.com/users/faisalcse/starred{/owner}{/repo}",
                "subscriptions_url": "https://api.github.com/users/faisalcse/subscriptions",
                "type": "User",
                "url": "https://api.github.com/users/faisalcse"
            }
        }
    ],
    "comments": 5,
    "comments_url": "https://api.github.com/repos/venomous0x/WhatsAPI/issues/616/comments",
    "created_at": "2014-02-08T11:39:45Z",
    "event_data": [
        {
            "actor": {
                "avatar_url": "https://avatars.githubusercontent.com/u/1610953?v=3",
                "events_url": "https://api.github.com/users/shirioko/events{/privacy}",
                "followers_url": "https://api.github.com/users/shirioko/followers",
                "following_url": "https://api.github.com/users/shirioko/following{/other_user}",
                "gists_url": "https://api.github.com/users/shirioko/gists{/gist_id}",
                "gravatar_id": "",
                "html_url": "https://github.com/shirioko",
                "id": 1610953,
                "login": "shirioko",
                "organizations_url": "https://api.github.com/users/shirioko/orgs",
                "received_events_url": "https://api.github.com/users/shirioko/received_events",
                "repos_url": "https://api.github.com/users/shirioko/repos",
                "site_admin": false,
                "starred_url": "https://api.github.com/users/shirioko/starred{/owner}{/repo}",
                "subscriptions_url": "https://api.github.com/users/shirioko/subscriptions",
                "type": "User",
                "url": "https://api.github.com/users/shirioko"
            },
            "commit_id": null,
            "created_at": "2014-02-08T12:54:20Z",
            "event": "closed",
            "id": 91906884,
            "url": "https://api.github.com/repos/venomous0x/WhatsAPI/issues/events/91906884"
        },
        {
            "actor": {
                "avatar_url": "https://avatars.githubusercontent.com/u/6623848?v=3",
                "events_url": "https://api.github.com/users/kmpslm/events{/privacy}",
                "followers_url": "https://api.github.com/users/kmpslm/followers",
                "following_url": "https://api.github.com/users/kmpslm/following{/other_user}",
                "gists_url": "https://api.github.com/users/kmpslm/gists{/gist_id}",
                "gravatar_id": "",
                "html_url": "https://github.com/kmpslm",
                "id": 6623848,
                "login": "kmpslm",
                "organizations_url": "https://api.github.com/users/kmpslm/orgs",
                "received_events_url": "https://api.github.com/users/kmpslm/received_events",
                "repos_url": "https://api.github.com/users/kmpslm/repos",
                "site_admin": false,
                "starred_url": "https://api.github.com/users/kmpslm/starred{/owner}{/repo}",
                "subscriptions_url": "https://api.github.com/users/kmpslm/subscriptions",
                "type": "User",
                "url": "https://api.github.com/users/kmpslm"
            },
            "commit_id": null,
            "created_at": "2014-02-08T13:48:35Z",
            "event": "mentioned",
            "id": 91909516,
            "url": "https://api.github.com/repos/venomous0x/WhatsAPI/issues/events/91909516"
        },
        {
            "actor": {
                "avatar_url": "https://avatars.githubusercontent.com/u/6623848?v=3",
                "events_url": "https://api.github.com/users/kmpslm/events{/privacy}",
                "followers_url": "https://api.github.com/users/kmpslm/followers",
                "following_url": "https://api.github.com/users/kmpslm/following{/other_user}",
                "gists_url": "https://api.github.com/users/kmpslm/gists{/gist_id}",
                "gravatar_id": "",
                "html_url": "https://github.com/kmpslm",
                "id": 6623848,
                "login": "kmpslm",
                "organizations_url": "https://api.github.com/users/kmpslm/orgs",
                "received_events_url": "https://api.github.com/users/kmpslm/received_events",
                "repos_url": "https://api.github.com/users/kmpslm/repos",
                "site_admin": false,
                "starred_url": "https://api.github.com/users/kmpslm/starred{/owner}{/repo}",
                "subscriptions_url": "https://api.github.com/users/kmpslm/subscriptions",
                "type": "User",
                "url": "https://api.github.com/users/kmpslm"
            },
            "commit_id": null,
            "created_at": "2014-02-08T13:48:35Z",
            "event": "subscribed",
            "id": 91909517,
            "url": "https://api.github.com/repos/venomous0x/WhatsAPI/issues/events/91909517"
        }
    ],
    "events_url": "https://api.github.com/repos/venomous0x/WhatsAPI/issues/616/events",
    "html_url": "https://github.com/venomous0x/WhatsAPI/issues/616",
    "id": 27198831,
    "labels": [],
    "labels_url": "https://api.github.com/repos/venomous0x/WhatsAPI/issues/616/labels{/name}",
    "locked": false,
    "milestone": null,
    "number": 616,
    "state": "closed",
    "title": "ContactSync.Cs Problem ..Help ME ",
    "updated_at": "2014-02-08T15:57:44Z",
    "url": "https://api.github.com/repos/venomous0x/WhatsAPI/issues/616",
    "user": {
        "avatar_url": "https://avatars.githubusercontent.com/u/6623848?v=3",
        "events_url": "https://api.github.com/users/kmpslm/events{/privacy}",
        "followers_url": "https://api.github.com/users/kmpslm/followers",
        "following_url": "https://api.github.com/users/kmpslm/following{/other_user}",
        "gists_url": "https://api.github.com/users/kmpslm/gists{/gist_id}",
        "gravatar_id": "",
        "html_url": "https://github.com/kmpslm",
        "id": 6623848,
        "login": "kmpslm",
        "organizations_url": "https://api.github.com/users/kmpslm/orgs",
        "received_events_url": "https://api.github.com/users/kmpslm/received_events",
        "repos_url": "https://api.github.com/users/kmpslm/repos",
        "site_admin": false,
        "starred_url": "https://api.github.com/users/kmpslm/starred{/owner}{/repo}",
        "subscriptions_url": "https://api.github.com/users/kmpslm/subscriptions",
        "type": "User",
        "url": "https://api.github.com/users/kmpslm"
    }
}